aimojicommit/AIManager.py
aimojicommit/ChoicesManager.py
aimojicommit/ConfigManager.py
aimojicommit/GitManager.py
aimojicommit/__init__.py
aimojicommit/aimojicommit.py
aimojicommit/constants.py
aimojicommit-1.0.0.data/data/requirements.txt
src/AIManager.py
src/ChoicesManager.py
src/ConfigManager.py
src/GitManager.py
src/aimojicommit.py
src/constants.py
aimojicommit-1.0.0.dist-info/METADATA
aimojicommit-1.0.0.dist-info/WHEEL
aimojicommit-1.0.0.dist-info/entry_points.txt
aimojicommit-1.0.0.dist-info/top_level.txt
aimojicommit-1.0.0.dist-info/RECORD
