Metadata-Version: 2.1
Name: aimojicommit
Version: 1.0.0
Summary: AI commit generator with OpenAI
Author: Luca Pasini
Author-email: luca.pasini.26@gmail.com
Requires-Dist: click (==8.1.4)
Requires-Dist: pick (==2.2.0)
Requires-Dist: tiktoken (==0.4.0)
Requires-Dist: openai (==0.27.8)
